fred_quincast/__init__.py
fred_quincast/ts.py
fred_quincast-0.2.1.dist-info/licenses/LICENSE
fred_quincast-0.2.1.dist-info/METADATA
fred_quincast-0.2.1.dist-info/WHEEL
fred_quincast-0.2.1.dist-info/top_level.txt
fred_quincast-0.2.1.dist-info/RECORD
